{"errors":[],"warnings":[],"namedChunkGroups":{"polyfill":{"chunks":[3,0,8],"assets":["webpack-runtime-87fd78c71210fb303722.js","webpack-runtime-87fd78c71210fb303722.js.map","commons-9ec57efe5528dec94528.js","commons-9ec57efe5528dec94528.js.map","polyfill-e1ddb3f078e444410f92.js","polyfill-e1ddb3f078e444410f92.js.map"],"children":{},"childAssets":{}},"app":{"chunks":[3,1,7,0,4],"assets":["webpack-runtime-87fd78c71210fb303722.js","webpack-runtime-87fd78c71210fb303722.js.map","styles.b70c291acd6b538cb712.css","styles-c2fe8482057191dca484.js","styles-c2fe8482057191dca484.js.map","framework-fd2b85530eec85104a39.js","framework-fd2b85530eec85104a39.js.map","commons-9ec57efe5528dec94528.js","commons-9ec57efe5528dec94528.js.map","app-0b5930ae14507bc78c8e.js","app-0b5930ae14507bc78c8e.js.map"],"children":{},"childAssets":{}},"component---src-pages-about-js":{"chunks":[1,2,0,5],"assets":["styles.b70c291acd6b538cb712.css","styles-c2fe8482057191dca484.js","styles-c2fe8482057191dca484.js.map","d2f59b09-4fb2dfbf286b33319f19.js","d2f59b09-4fb2dfbf286b33319f19.js.map","commons-9ec57efe5528dec94528.js","commons-9ec57efe5528dec94528.js.map","component---src-pages-about-js-44a066fc15d09ee2aec5.js","component---src-pages-about-js-44a066fc15d09ee2aec5.js.map"],"children":{},"childAssets":{}},"component---src-pages-index-js":{"chunks":[1,2,0,6],"assets":["styles.b70c291acd6b538cb712.css","styles-c2fe8482057191dca484.js","styles-c2fe8482057191dca484.js.map","d2f59b09-4fb2dfbf286b33319f19.js","d2f59b09-4fb2dfbf286b33319f19.js.map","commons-9ec57efe5528dec94528.js","commons-9ec57efe5528dec94528.js.map","component---src-pages-index-js-bc61c51ade5dcbbc2fb2.js","component---src-pages-index-js-bc61c51ade5dcbbc2fb2.js.map"],"children":{},"childAssets":{}}},"assetsByChunkName":{"polyfill":["webpack-runtime-87fd78c71210fb303722.js","commons-9ec57efe5528dec94528.js","polyfill-e1ddb3f078e444410f92.js"],"app":["webpack-runtime-87fd78c71210fb303722.js","styles.b70c291acd6b538cb712.css","styles-c2fe8482057191dca484.js","framework-fd2b85530eec85104a39.js","commons-9ec57efe5528dec94528.js","app-0b5930ae14507bc78c8e.js"],"component---src-pages-about-js":["styles.b70c291acd6b538cb712.css","styles-c2fe8482057191dca484.js","d2f59b09-4fb2dfbf286b33319f19.js","commons-9ec57efe5528dec94528.js","component---src-pages-about-js-44a066fc15d09ee2aec5.js"],"component---src-pages-index-js":["styles.b70c291acd6b538cb712.css","styles-c2fe8482057191dca484.js","d2f59b09-4fb2dfbf286b33319f19.js","commons-9ec57efe5528dec94528.js","component---src-pages-index-js-bc61c51ade5dcbbc2fb2.js"]}}